onlinechoir/__init__.py
onlinechoir/common/__init__.py
onlinechoir/common/audio_codecs.py
onlinechoir/common/audio_devices.py
onlinechoir/common/audio_files.py
onlinechoir/common/auth.py
onlinechoir/common/config.py
onlinechoir/common/constants.py
onlinechoir/common/log.py
onlinechoir/common/message_board.py
onlinechoir/common/message_protocol.py
onlinechoir/common/network.py
onlinechoir/common/pace_maker.py
onlinechoir/common/platform.py
onlinechoir/common/prompt.py
onlinechoir/common/singleton.py
onlinechoir/common/utils.py
onlinechoir/common/version.py
onlinechoir/master/__init__.py
onlinechoir/master/gui.py
onlinechoir/master/master_client.py
onlinechoir/master/mixing_desk.py
onlinechoir/server/__init__.py
onlinechoir/server/audio_broadcaster.py
onlinechoir/server/audio_mixer.py
onlinechoir/server/server.py
onlinechoir/server/web_radio.py
onlinechoir/slave/__init__.py
onlinechoir/slave/calibration_tool.py
onlinechoir/slave/db_calculator.py
onlinechoir/slave/gui.py
onlinechoir/slave/gui_enums.py
onlinechoir/slave/level_meter.py
onlinechoir/slave/signal_smoother.py
onlinechoir/slave/slave_client.py
onlinechoir/slave/sound_card.py
onlinechoir/slave/data/output_test.wav
online_choir-1.1.3.dist-info/LICENSE
online_choir-1.1.3.dist-info/METADATA
online_choir-1.1.3.dist-info/WHEEL
online_choir-1.1.3.dist-info/entry_points.txt
online_choir-1.1.3.dist-info/top_level.txt
online_choir-1.1.3.dist-info/RECORD
