Metadata-Version: 2.1
Name: online-choir
Version: 1.1.3
Summary: A tool to sing together online
Home-page: https://gitlab.com/odousse/online-choir
Author: Olivier Dousse
Author-email: olivier@modetexte.ch
Project-URL: Bug Tracker, https://gitlab.com/odousse/online-choir/-/issues
Classifier: Programming Language :: Python :: 3
Classifier: License :: OSI Approved :: GNU Affero General Public License v3 or later (AGPLv3+)
Classifier: Operating System :: OS Independent
Requires-Python: >=3.7
License-File: LICENSE
Requires-Dist: numpy
Requires-Dist: psutil
Requires-Dist: sounddevice
Requires-Dist: soundfile
Requires-Dist: uvloop
